pergamon_theme/__init__.py
pergamon_theme/_version.py
pergamon_theme/labextension/build_log.json
pergamon_theme/labextension/package.json
pergamon_theme/labextension/schemas/pergamon_theme/package.json.orig
pergamon_theme/labextension/schemas/pergamon_theme/plugin.json
pergamon_theme/labextension/static/lib_index_js.75db2d6a1f39abdd613f.js
pergamon_theme/labextension/static/lib_index_js.75db2d6a1f39abdd613f.js.map
pergamon_theme/labextension/static/remoteEntry.274ae810bc70cdcfe6ba.js
pergamon_theme/labextension/static/remoteEntry.274ae810bc70cdcfe6ba.js.map
pergamon_theme/labextension/static/style.js
pergamon_theme/labextension/themes/pergamon_theme/5410e33b765240edc652.png
pergamon_theme/labextension/themes/pergamon_theme/index.css
pergamon_theme/labextension/themes/pergamon_theme/index.js
pergamon_theme-0.1.17.data/data/share/jupyter/labextensions/pergamon_theme/build_log.json
pergamon_theme-0.1.17.data/data/share/jupyter/labextensions/pergamon_theme/package.json
pergamon_theme-0.1.17.data/data/share/jupyter/labextensions/pergamon_theme/schemas/pergamon_theme/package.json.orig
pergamon_theme-0.1.17.data/data/share/jupyter/labextensions/pergamon_theme/schemas/pergamon_theme/plugin.json
pergamon_theme-0.1.17.data/data/share/jupyter/labextensions/pergamon_theme/static/lib_index_js.75db2d6a1f39abdd613f.js
pergamon_theme-0.1.17.data/data/share/jupyter/labextensions/pergamon_theme/static/lib_index_js.75db2d6a1f39abdd613f.js.map
pergamon_theme-0.1.17.data/data/share/jupyter/labextensions/pergamon_theme/static/remoteEntry.274ae810bc70cdcfe6ba.js
pergamon_theme-0.1.17.data/data/share/jupyter/labextensions/pergamon_theme/static/remoteEntry.274ae810bc70cdcfe6ba.js.map
pergamon_theme-0.1.17.data/data/share/jupyter/labextensions/pergamon_theme/static/style.js
pergamon_theme-0.1.17.data/data/share/jupyter/labextensions/pergamon_theme/themes/pergamon_theme/5410e33b765240edc652.png
pergamon_theme-0.1.17.dist-info/METADATA
pergamon_theme-0.1.17.dist-info/WHEEL
pergamon_theme-0.1.17.dist-info/licenses/LICENSE
pergamon_theme-0.1.17.dist-info/RECORD
