Metadata-Version: 2.4
Name: pergamon_theme
Version: 0.1.17
Dynamic: Keywords
Summary: Pergamon Theme Extension.
Project-URL: Homepage, https://www.weareconflict.com
Project-URL: Bug Tracker, https://www.weareconflict.com/issues
Project-URL: Repository, https://www.github.com/calliopeai
Author: Calliope
License: BSD 3-Clause License
License-File: LICENSE
Classifier: Framework :: Jupyter
Classifier: Framework :: Jupyter :: JupyterLab
Classifier: Framework :: Jupyter :: JupyterLab :: 4
Classifier: Framework :: Jupyter :: JupyterLab :: Extensions
Classifier: Framework :: Jupyter :: JupyterLab :: Extensions :: Prebuilt
Classifier: License :: OSI Approved :: BSD License
Classifier: Programming Language :: Python
Classifier: Programming Language :: Python :: 3
Classifier: Programming Language :: Python :: 3.8
Classifier: Programming Language :: Python :: 3.9
Classifier: Programming Language :: Python :: 3.10
Classifier: Programming Language :: Python :: 3.11
Classifier: Programming Language :: Python :: 3.12
Requires-Python: >=3.8
